yoctol_argparse/__init__.py
yoctol_argparse/__version__.py
yoctol_argparse/actions.py
yoctol_argparse/formatters.py
yoctol_argparse/parser.py
yoctol_argparse/types.py
yoctol_argparse/tests/__init__.py
yoctol_argparse/tests/test_actions.py
yoctol_argparse/tests/test_parser.py
yoctol_argparse/tests/test_types.py
yoctol_argparse-0.3.0.dist-info/LICENSE
yoctol_argparse-0.3.0.dist-info/METADATA
yoctol_argparse-0.3.0.dist-info/WHEEL
yoctol_argparse-0.3.0.dist-info/top_level.txt
yoctol_argparse-0.3.0.dist-info/RECORD
