Metadata-Version: 2.1
Name: yoctol-argparse
Version: 0.3.0
Summary: Argument Parser created by Yoctol
Home-page: UNKNOWN
Author: noobOriented
Author-email: jsaon@yoctol.com
License: MIT
Platform: UNKNOWN
Requires-Python: >=3.6
